setup.py
pygments_style_cheerfully_dark/__init__.py
pygments_style_cheerfully_dark.egg-info/PKG-INFO
pygments_style_cheerfully_dark.egg-info/SOURCES.txt
pygments_style_cheerfully_dark.egg-info/dependency_links.txt
pygments_style_cheerfully_dark.egg-info/entry_points.txt
pygments_style_cheerfully_dark.egg-info/requires.txt
pygments_style_cheerfully_dark.egg-info/top_level.txt