Metadata-Version: 1.1
Name: pygments-style-cheerfully-dark
Version: 0.1
Summary: Pygments version of the "Cheerfully Dark" Sublime Text theme.
Home-page: https://github.com/jorgehatccrma/pygments-style-cheerfully-dark
Author: Jorge Herrera
Author-email: jherreras@gmail.com
License: BSD
Platform: UNKNOWN
Classifier: Development Status :: 4 - Beta
Classifier: Environment :: Plugins
Classifier: Intended Audience :: Developers
Classifier: License :: OSI Approved :: BSD License
Classifier: Operating System :: OS Independent
Classifier: Programming Language :: Python
Classifier: Programming Language :: Python :: 2
Classifier: Programming Language :: Python :: 3
Classifier: Topic :: Software Development :: Libraries :: Python Modules
